bioturing_connector/__init__.py
bioturing_connector/bbrowserx_connector.py
bioturing_connector/common/__init__.py
bioturing_connector/common/common.py
bioturing_connector/common/constants.py
bioturing_connector/common/https_agent.py
bioturing_connector/connector.py
bioturing_connector/lens_bulk_connector.py
bioturing_connector/lens_sc_connector.py
bioturing_connector/typing/__init__.py
bioturing_connector-1.14.0.dist-info/METADATA
bioturing_connector-1.14.0.dist-info/WHEEL
bioturing_connector-1.14.0.dist-info/RECORD
