Metadata-Version: 2.1
Name: bioturing-connector
Version: 1.14.0
Summary: A set of python modules for accessing Bioturing's services on private server
Author: BioTuring
Author-email: support@bioturing.com
Requires-Python: >=3.7,<4.0
Classifier: Programming Language :: Python :: 3
Classifier: Programming Language :: Python :: 3.7
Classifier: Programming Language :: Python :: 3.8
Classifier: Programming Language :: Python :: 3.9
Classifier: Programming Language :: Python :: 3.10
Classifier: Programming Language :: Python :: 3.11
Classifier: Programming Language :: Python :: 3.12
Requires-Dist: numpy
Requires-Dist: pandas
Requires-Dist: requests
Requires-Dist: requests_toolbelt (>=1.0.0)
Requires-Dist: scipy
Requires-Dist: tqdm
